{
  "formatVersion": 1,
  "database": {
    "version": 1,
    "identityHash": "ee61cfcfc5dc4a3d7fdc36ed08c3ecf5",
    "entities": [
      {
        "tableName": "Pokemon",
        "createSql": "CREATE TABLE IF NOT EXISTS `${TABLE_NAME}` (`name` TEXT NOT NULL, `url` TEXT NOT NULL, PRIMARY KEY(`name`))",
        "fields": [
          {
            "fieldPath": "name",
            "columnName": "name",
            "affinity": "TEXT",
            "notNull": true
          },
          {
            "fieldPath": "url",
            "columnName": "url",
            "affinity": "TEXT",
            "notNull": true
          }
        ],
        "primaryKey": {
          "columnNames": [
            "name"
          ],
          "autoGenerate": false
        },
        "indices": [],
        "foreignKeys": []
      }
    ],
    "views": [],
    "setupQueries": [
      "CREATE TABLE IF NOT EXISTS room_master_table (id INTEGER PRIMARY KEY,identity_hash TEXT)",
      "INSERT OR REPLACE INTO room_master_table (id,identity_hash) VALUES(42, 'ee61cfcfc5dc4a3d7fdc36ed08c3ecf5')"
    ]
  }
}